grn_thresholding/__init__.py
grn_thresholding/methods/__init__.py
grn_thresholding/methods/bimodal_thresholding.py
grn_thresholding/methods/hard_thresholding.py
grn_thresholding/methods/homogeneous_thresholding.py
grn_thresholding/methods/max_f1_score.py
grn_thresholding/methods/soft_trhesholding.py
grn_thresholding/methods/top_edges.py
grn_thresholding-0.0.1.dist-info/LICENSE
grn_thresholding-0.0.1.dist-info/METADATA
grn_thresholding-0.0.1.dist-info/WHEEL
grn_thresholding-0.0.1.dist-info/top_level.txt
grn_thresholding-0.0.1.dist-info/RECORD
