Metadata-Version: 2.1
Name: grn-thresholding
Version: 0.0.1
Summary: A collection of thesholding methods for GRNs
Home-page: https://github.com/soelmicheletti/grn-thresholding
Author: Soel Micheletti
Author-email: msoel@ethz.ch
License: MIT
Keywords: statistics,causality
Classifier: Development Status :: 4 - Beta
Classifier: Intended Audience :: Developers
Classifier: Topic :: Scientific/Engineering :: Artificial Intelligence
Classifier: License :: OSI Approved :: MIT License
Classifier: Programming Language :: Python :: 3.8
License-File: LICENSE
Requires-Dist: mixem (>=0.1.4)
Requires-Dist: scikit-learn
Requires-Dist: pandas
Requires-Dist: numpy
